<?xml version="1.0" encoding="UTF-8"?>
<objects serializationModel="Studio.01.10.00">
    <object class="AudioFile" id="{129fe132-52a6-4b2d-a5e8-487ff85d3669}">
        <property name="assetPath">
            <value>winning.wav</value>
        </property>
        <property name="frequencyInKHz">
            <value>44.0999985</value>
        </property>
        <property name="channelCount">
            <value>2</value>
        </property>
        <property name="length">
            <value>5.0155102040816324</value>
        </property>
        <relationship name="masterAssetFolder">
            <destination>{34e4fbb0-d02f-41be-84d4-b03ce746006e}</destination>
        </relationship>
    </object>
</objects>
